{
  "bids_meta": {
    "dataset": "ds004024",
    "modality": "T1w",
    "session_id": "mri",
    "subject_id": "CON021"
  },
  "cjv": 0.2621107741717321,
  "cnr": 4.248692733189481,
  "efc": 0.7807894529685542,
  "fber": 12.49945664935045,
  "fwhm_avg": 4.531609459790056,
  "fwhm_x": 4.598949451762503,
  "fwhm_y": 4.6085894506133265,
  "fwhm_z": 4.387289476994338,
  "icvs_csf": 0.28358810991971717,
  "icvs_gm": 0.37711131847395624,
  "icvs_wm": 0.3393005716063266,
  "inu_med": 0.22249813377857208,
  "inu_range": 0.014175862073898315,
  "provenance": {
    "md5sum": "d4f8b63ee0799d40f6faa095c1ca6faa",
    "settings": {
      "testing": false
    },
    "software": "mriqc",
    "version": "23.0.1",
    "warnings": {
      "large_rot_frame": true,
      "small_air_mask": true
    },
    "webapi_port": null,
    "webapi_url": "https://mriqc.nimh.nih.gov/api/v1"
  },
  "qi_1": 0.0,
  "qi_2": 0.0013653676154808012,
  "rpve_csf": 26.083477900786466,
  "rpve_gm": 17.36718822904008,
  "rpve_wm": 28.42680463210162,
  "size_x": 256,
  "size_y": 256,
  "size_z": 256,
  "snr_csf": 2.99192975334,
  "snr_gm": 9.253267751250009,
  "snr_total": 33.53525028721826,
  "snr_wm": 88.36055335706477,
  "snrd_csf": -1.0,
  "snrd_gm": -1.0,
  "snrd_total": -1.0,
  "snrd_wm": -1.0,
  "spacing_x": 1.0000001192092896,
  "spacing_y": 1.0000001192092896,
  "spacing_z": 1.0000001192092896,
  "summary_bg_k": 0.0,
  "summary_bg_mad": 0.0,
  "summary_bg_mean": 0.0,
  "summary_bg_median": 0.0,
  "summary_bg_n": 1.0,
  "summary_bg_p05": 0.0,
  "summary_bg_p95": 0.0,
  "summary_bg_stdv": 0.0,
  "summary_csf_k": -0.12058365095963763,
  "summary_csf_mad": 94.3723404639232,
  "summary_csf_mean": 286.5153393632344,
  "summary_csf_median": 296.3178967013955,
  "summary_csf_n": 14479.0,
  "summary_csf_p05": 105.77843441292644,
  "summary_csf_p95": 433.2737252242863,
  "summary_csf_stdv": 99.03563528377668,
  "summary_gm_k": 0.46460744792882736,
  "summary_gm_mad": 70.831402994236,
  "summary_gm_mean": 687.233310227289,
  "summary_gm_median": 683.0807866305113,
  "summary_gm_n": 23440.0,
  "summary_gm_p05": 572.597202681005,
  "summary_gm_p95": 817.9061330907047,
  "summary_gm_stdv": 73.81891824614452,
  "summary_wm_k": -0.49638413197397346,
  "summary_wm_mad": 12.336643180317083,
  "summary_wm_mean": 1001.2136874186124,
  "summary_wm_median": 1000.3819217607379,
  "summary_wm_n": 193642.0,
  "summary_wm_p05": 984.8052840381861,
  "summary_wm_p95": 1021.2244679778814,
  "summary_wm_stdv": 11.321560364660156,
  "tpm_overlap_csf": 0.14799391656898261,
  "tpm_overlap_gm": 0.4362842250757258,
  "tpm_overlap_wm": 0.48893964831884573,
  "wm2max": 0.8891784157044408
}